gaitalytics/__init__.py
gaitalytics/api.py
gaitalytics/events.py
gaitalytics/features.py
gaitalytics/io.py
gaitalytics/mapping.py
gaitalytics/model.py
gaitalytics/normalisation.py
gaitalytics/segmentation.py
gaitalytics/utils/__init__.py
gaitalytics/utils/linalg.py
gaitalytics/utils/math.py
gaitalytics/utils/mocap.py
gaitalytics-0.2.2.dist-info/AUTHORS.rst
gaitalytics-0.2.2.dist-info/LICENSE
gaitalytics-0.2.2.dist-info/METADATA
gaitalytics-0.2.2.dist-info/WHEEL
gaitalytics-0.2.2.dist-info/top_level.txt
gaitalytics-0.2.2.dist-info/RECORD
