Metadata-Version: 2.1
Name: gaitalytics
Version: 0.2.2
Summary: easy gait-metrics for everyone
Author-email: André Böni <andre.boeni@llui.org>
Maintainer-email: André Böni <andre.boeni@llui.org>
License: MIT License
Project-URL: Homepage, https://github.com/DART-Lab-LLUI/python-gaitalytics
Project-URL: Documentation, https://python-gaitalytics.readthedocs.io
Project-URL: Repository, https://github.com/DART-Lab-LLUI/python-gaitalytics
Project-URL: Issues, https://github.com/DART-Lab-LLUI/python-gaitalytics/issues
Project-URL: Changelog, https://github.com/me/spam/blob/master/CHANGELOG.md
Keywords: gait-analysis,mocap,c3d,gait-metrics,biomechanics
Classifier: Development Status :: 4 - Beta
Classifier: Intended Audience :: Science/Research
Classifier: Topic :: Scientific/Engineering :: Bio-Informatics
Classifier: Topic :: Utilities
Classifier: License :: OSI Approved :: MIT License
Classifier: Programming Language :: Python :: 3
Classifier: Programming Language :: Python :: 3.11
Classifier: Programming Language :: Python :: 3.12
Classifier: Programming Language :: Python :: 3.13
Classifier: Operating System :: OS Independent
Requires-Python: >=3.11
License-File: LICENSE
License-File: AUTHORS.rst
Requires-Dist: h5netcdf>=1.3.0
Requires-Dist: pandas>=1.5
Requires-Dist: pyyaml>=6.0.1
Requires-Dist: scipy>=1.13
Requires-Dist: numpy>=1.23
Requires-Dist: pyomeca>=2024.0
Requires-Dist: ezc3d>=1.5.17
Requires-Dist: xarray>=2024.9
Provides-Extra: dev
Requires-Dist: ruff; extra == "dev"
Requires-Dist: mypy; extra == "dev"
Requires-Dist: pip; extra == "dev"
Requires-Dist: types-PyYAML; extra == "dev"
Provides-Extra: test
Requires-Dist: pytest; extra == "test"
Requires-Dist: pytest-cov; extra == "test"
Provides-Extra: build
Requires-Dist: build; extra == "build"
Requires-Dist: setuptools>=64; extra == "build"
Requires-Dist: setuptools_scm>=8; extra == "build"
Provides-Extra: docs
Requires-Dist: sphinx; extra == "docs"
Requires-Dist: setuptools>=64; extra == "docs"
Requires-Dist: sphinx-rtd-theme; extra == "docs"
Requires-Dist: sphinx-autodoc-typehints; extra == "docs"
Requires-Dist: sphinx_github_changelog; extra == "docs"
Requires-Dist: sphinx-codeautolink; extra == "docs"
Requires-Dist: sphinxcontrib-bibtex; extra == "docs"
Requires-Dist: sphinxcontrib-mermaid; extra == "docs"
